rtl/axi_lite_slave.v
module axi_lite_slave (
    input  wire        clk,
    input  wire        rst,

    // Write address channel
    input  wire        awvalid,
    input  wire [31:0] awaddr,
    output reg         awready,

    // Write data channel
    input  wire        wvalid,
    input  wire [31:0] wdata,
    output reg         wready,

    // Write response channel
    output reg         bvalid,
    input  wire        bready,

    // Read address channel
    input  wire        arvalid,
    input  wire [31:0] araddr,
    output reg         arready,

    // Read data channel
    output reg         rvalid,
    output reg [31:0]  rdata,
    input  wire        rready
);

    // Simple register map
    reg [31:0] reg0;

    always @(posedge clk) begin
        if (rst) begin
            awready <= 0;
            wready  <= 0;
            bvalid  <= 0;
            arready <= 0;
            rvalid  <= 0;
            reg0    <= 0;
        end else begin
            // WRITE HANDSHAKE
            if (awvalid && !awready)
                awready <= 1;
            else
                awready <= 0;

            if (wvalid && !wready)
                wready <= 1;
            else
                wready <= 0;

            if (awvalid && wvalid) begin
                reg0 <= wdata;
                bvalid <= 1;
            end else if (bready) begin
                bvalid <= 0;
            end

            // READ HANDSHAKE
            if (arvalid && !arready) begin
                arready <= 1;
                rdata <= reg0;
                rvalid <= 1;
            end else if (rready) begin
                rvalid <= 0;
                arready <= 0;
            end
        end
    end

endmodule

tb/tb_axi_lite.v
module tb_axi_lite;
    reg clk = 0;
    reg rst = 1;

    always #5 clk = ~clk;

    reg awvalid;
    reg [31:0] awaddr;
    wire awready;

    reg wvalid;
    reg [31:0] wdata;
    wire wready;

    wire bvalid;
    reg bready;

    reg arvalid;
    reg [31:0] araddr;
    wire arready;

    wire rvalid;
    wire [31:0] rdata;
    reg rready;

    axi_lite_slave dut (
        .clk(clk), .rst(rst),
        .awvalid(awvalid), .awaddr(awaddr), .awready(awready),
        .wvalid(wvalid), .wdata(wdata), .wready(wready),
        .bvalid(bvalid), .bready(bready),
        .arvalid(arvalid), .araddr(araddr), .arready(arready),
        .rvalid(rvalid), .rdata(rdata), .rready(rready)
    );

    initial begin
        $dumpfile("waveforms/axi.vcd");
        $dumpvars(0, tb_axi_lite);

        // Reset
        #20 rst = 0;

        // Write
        awaddr = 32'h0;
        awvalid = 1;
        wdata = 32'hDEADBEEF;
        wvalid = 1;
        bready = 1;

        #20;
        awvalid = 0;
        wvalid = 0;

        // Read
        araddr = 32'h0;
        arvalid = 1;
        rready = 1;

        #40 $finish;
    end
endmodule

waveforms/axi.vcd
$date
	Sun Feb 01 19:11:08 2026
$end
$version
	Icarus Verilog
$end
$timescale
	1s
$end
$scope module tb_axi_lite $end
$var wire 1 ! wready $end
$var wire 1 " rvalid $end
$var wire 32 # rdata [31:0] $end
$var wire 1 $ bvalid $end
$var wire 1 % awready $end
$var wire 1 & arready $end
$var reg 32 ' araddr [31:0] $end
$var reg 1 ( arvalid $end
$var reg 32 ) awaddr [31:0] $end
$var reg 1 * awvalid $end
$var reg 1 + bready $end
$var reg 1 , clk $end
$var reg 1 - rready $end
$var reg 1 . rst $end
$var reg 32 / wdata [31:0] $end
$var reg 1 0 wvalid $end
$scope module dut $end
$var wire 32 1 araddr [31:0] $end
$var wire 1 ( arvalid $end
$var wire 32 2 awaddr [31:0] $end
$var wire 1 * awvalid $end
$var wire 1 + bready $end
$var wire 1 , clk $end
$var wire 1 - rready $end
$var wire 1 . rst $end
$var wire 32 3 wdata [31:0] $end
$var wire 1 0 wvalid $end
$var reg 1 & arready $end
$var reg 1 % awready $end
$var reg 1 $ bvalid $end
$var reg 32 4 rdata [31:0] $end
$var reg 32 5 reg0 [31:0] $end
$var reg 1 " rvalid $end
$var reg 1 ! wready $end
$upscope $end
$upscope $end
$enddefinitions $end
$comment Show the parameter values. $end
$dumpall
$end
#0
$dumpvars
bx 5
bx 4
bx 3
bx 2
bx 1
x0
bx /
1.
x-
0,
x+
x*
bx )
x(
bx '
x&
x%
x$
bx #
x"
x!
$end
#5
b0 5
0"
0&
0$
0!
0%
1,
#10
0,
#15
1,
#20
0,
1+
10
b11011110101011011011111011101111 /
b11011110101011011011111011101111 3
1*
b0 )
b0 2
0.
#25
1$
b11011110101011011011111011101111 5
1!
1%
1,
#30
0,
#35
0!
0%
1,
#40
0,
1-
1(
b0 '
b0 1
00
0*
#45
1"
b11011110101011011011111011101111 #
b11011110101011011011111011101111 4
1&
0$
1,
#50
0,
#55
0&
0"
1,
#60
0,
#65
1"
1&
1,
#70
0,
#75
0&
0"
1,
